dev_helper/__init__.py
dev_helper/core/__init__.py
dev_helper/core/config.py
dev_helper/core/logging.py
dev_helper/decorators/__init__.py
dev_helper/decorators/robustness.py
dev_helper/decorators/timing.py
dev_helper/utils/__init__.py
dev_helper/utils/formatting.py
dev_helper/utils/io.py
dev_helper/utils/text.py
pydevhelper-0.3.0.dist-info/METADATA
pydevhelper-0.3.0.dist-info/WHEEL
pydevhelper-0.3.0.dist-info/licenses/LICENSE
pydevhelper-0.3.0.dist-info/RECORD
