Metadata-Version: 2.4
Name: pydevhelper
Version: 0.3.0
Summary: Um toolkit de produtividade para desenvolvedores em Python
Project-URL: Homepage, https://github.com/juliobrige/DevHelper
Project-URL: Bug Tracker, https://github.com/juliobrige/DevHelper/issues
Author-email: juliobrige <juliobenjamimbernardo36@gmail.com>
License: MIT
License-File: LICENSE
Requires-Python: >=3.9
Requires-Dist: rich
